kaamiki/__init__.py
kaamiki-0.0.0.dist-info/LICENSE
kaamiki-0.0.0.dist-info/METADATA
kaamiki-0.0.0.dist-info/WHEEL
kaamiki-0.0.0.dist-info/top_level.txt
kaamiki-0.0.0.dist-info/RECORD
