Metadata-Version: 2.1
Name: kaamiki
Version: 0.0.0
Summary: Kaamiki is a simple machine learning framework for obvious tasks.
Home-page: https://github.com/kaamiki/kaamiki
Author: Kaamiki Development Team
Author-email: xames3.kaamiki@gmail.com
Maintainer-email: xames3.kaamiki@gmail.com
License: Apache Software License 2.0
Keywords: kaamiki python
Platform: UNKNOWN
Classifier: Development Status :: 1 - Planning
Classifier: Intended Audience :: Developers
Classifier: Intended Audience :: End Users/Desktop
Classifier: Intended Audience :: Science/Research
Classifier: License :: OSI Approved :: Apache Software License
Classifier: Operating System :: OS Independent
Classifier: Programming Language :: Python
Classifier: Programming Language :: Python :: 3 :: Only
Classifier: Programming Language :: Python :: 3.6
Classifier: Programming Language :: Python :: 3.7
Classifier: Programming Language :: Python :: 3.8
Classifier: Topic :: Home Automation
Classifier: Topic :: Security
Classifier: Topic :: Security :: Cryptography
Classifier: Topic :: Scientific/Engineering :: Artificial Intelligence
Requires-Python: >=3.6.9
Requires-Dist: psutil
